dt/__init__.py
dt/__main__.py
de_bucket_download-0.0.1.dist-info/LICENSE
de_bucket_download-0.0.1.dist-info/METADATA
de_bucket_download-0.0.1.dist-info/WHEEL
de_bucket_download-0.0.1.dist-info/top_level.txt
de_bucket_download-0.0.1.dist-info/RECORD
